tracardi_fullcontact_webhook/plugin.py
tracardi_fullcontact_webhook/model/configuration.py
tracardi_fullcontact_webhook/model/full_contact_source_configuration.py
tracardi_fullcontact_webhook/model/__pycache__/configuration.cpython-38.pyc
tracardi_fullcontact_webhook/model/__pycache__/full_contact_source_configuration.cpython-38.pyc
tracardi_fullcontact_webhook/test/manual_direct_test.py
tracardi_fullcontact_webhook/test/manual_test.py
tracardi_fullcontact_webhook-0.6.0.dist-info/LICENSE.md
tracardi_fullcontact_webhook-0.6.0.dist-info/METADATA
tracardi_fullcontact_webhook-0.6.0.dist-info/WHEEL
tracardi_fullcontact_webhook-0.6.0.dist-info/top_level.txt
tracardi_fullcontact_webhook-0.6.0.dist-info/RECORD
