Metadata-Version: 2.1
Name: tracardi-fullcontact-webhook
Version: 0.6.0
Summary: This plugin reads data from FullContact service about the provided e-mail.
Home-page: UNKNOWN
Author: Risto Kowaczewski
Author-email: risto.kowaczewski@gmail.com
License: UNKNOWN
Keywords: tracardi,plugin
Platform: UNKNOWN
Classifier: Programming Language :: Python :: 3
Classifier: License :: OSI Approved :: MIT License
Classifier: Operating System :: OS Independent
Requires-Python: >=3.8
License-File: LICENSE.md
Requires-Dist: tracardi-plugin-sdk (>=0.6.18)
Requires-Dist: tracardi
Requires-Dist: tracardi-dot-notation
Requires-Dist: pydantic
Requires-Dist: aiohttp
